MANIFEST.in
setup.py
Webalchemy.egg-info/PKG-INFO
Webalchemy.egg-info/SOURCES.txt
Webalchemy.egg-info/dependency_links.txt
Webalchemy.egg-info/not-zip-safe
Webalchemy.egg-info/requires.txt
Webalchemy.egg-info/top_level.txt
examples/__init__.py
examples/colors_meteor/__init__.py
examples/colors_meteor/colors_meteor_example.py
examples/hello_world/__init__.py
examples/hello_world/hello_world_example.py
examples/math_explorer/__init__.py
examples/math_explorer/math_explorer.py
examples/three_d_earth/__init__.py
examples/three_d_earth/freeze_app.py
examples/three_d_earth/serve_through_websocket.py
examples/three_d_earth/three_d_earth.py
examples/tictactoe/__init__.py
examples/tictactoe/board.py
examples/tictactoe/tictactoe_example.py
examples/todomvc/__init__.py
examples/todomvc/freeze_app.py
examples/todomvc/serve_through_websocket.py
examples/todomvc/todomvc.py
webalchemy/Stacker.py
webalchemy/__init__.py
webalchemy/config.py
webalchemy/htmlparser.py
webalchemy/main.html
webalchemy/mainhtml.py
webalchemy/monkeypatch.py
webalchemy/mvc.py
webalchemy/remotedocument.py
webalchemy/saferef.py
webalchemy/server.py
webalchemy/js/classy.js
webalchemy/js/comm.js
webalchemy/js/cookie.js
webalchemy/js/download_url.js
webalchemy/js/reconnecting_ws.js
webalchemy/js/reconnection_overlay.js
webalchemy/js/vendor.js
webalchemy/js/weba.js
webalchemy/stacker_wrappers/__init__.py
webalchemy/stacker_wrappers/bootstrap_3/__init__.py
webalchemy/stacker_wrappers/bootstrap_3/bootstrap3_wrapper.py
webalchemy/widgets/__init__.py
webalchemy/widgets/basic/__init__.py
webalchemy/widgets/basic/menu.py
webalchemy/widgets/basic/sort.py
webalchemy/widgets/basic/table.py