Metadata-Version: 1.1
Name: Webalchemy
Version: 0.3.8
Summary: Modern web development with Python
Home-page: https://github.com/skariel/webalchemy
Author: Jose Ariel Keselman
Author-email: skariel@gmail.com
License: MIT
Keywords: web development,websocket
Platform: UNKNOWN
Classifier: Topic :: Software Development :: Libraries
Classifier: Topic :: Software Development :: Libraries :: Python Modules
Classifier: Intended Audience :: Developers
Classifier: License :: OSI Approved :: MIT License
Classifier: Programming Language :: Python
Classifier: Programming Language :: Python :: 3
Classifier: Topic :: Internet :: WWW/HTTP :: Dynamic Content
